simon/__init__.py
simon/simon.py
simonspeckciphers-1.0.0.dist-info/METADATA
simonspeckciphers-1.0.0.dist-info/RECORD
simonspeckciphers-1.0.0.dist-info/WHEEL
simonspeckciphers-1.0.0.dist-info/top_level.txt
speck/__init__.py
speck/speck.py
