Metadata-Version: 2.1
Name: simonspeckciphers
Version: 1.0.0
Summary: Implementations of the NSA's Simon and Speck Block Ciphers
Home-page: https://github.com/inmcm/Simon_Speck_Ciphers/tree/master/Python/simonspeckciphers
Author: Calvin McCoy
Author-email: calvin.mccoy@protonmail.com
License: MIT
Download-URL: https://github.com/inmcm/Simon_Speck_Ciphers/archive/1.0.0.tar.gz
Keywords: cryptography cipher encryption decryption crypto
Platform: UNKNOWN
Classifier: Development Status :: 4 - Beta
Classifier: Intended Audience :: Developers
Classifier: Topic :: Security :: Cryptography
Classifier: License :: OSI Approved :: MIT License
Classifier: Programming Language :: Python :: 2
Classifier: Programming Language :: Python :: 2.7
Classifier: Programming Language :: Python :: 3
Classifier: Programming Language :: Python :: 3.4
Classifier: Programming Language :: Python :: 3.5
Classifier: Programming Language :: Python :: 3.6
